xarray_ms/__init__.py
xarray_ms/casa_types.py
xarray_ms/errors.py
xarray_ms/msv4_types.py
xarray_ms/multiton.py
xarray_ms/query.py
xarray_ms/utils.py
xarray_ms/backend/msv2/array.py
xarray_ms/backend/msv2/entrypoint.py
xarray_ms/backend/msv2/entrypoint_utils.py
xarray_ms/backend/msv2/imputation.py
xarray_ms/backend/msv2/measures_adapters.py
xarray_ms/backend/msv2/measures_encoders.py
xarray_ms/backend/msv2/partition.py
xarray_ms/backend/msv2/structure.py
xarray_ms/backend/msv2/table_utils.py
xarray_ms/backend/msv2/factories/__init__.py
xarray_ms/backend/msv2/factories/antenna.py
xarray_ms/backend/msv2/factories/core.py
xarray_ms/backend/msv2/factories/correlated.py
xarray_ms/backend/msv2/factories/field_and_source.py
xarray_ms/testing/__init__.py
xarray_ms/testing/simulator.py
xarray_ms/testing/utils.py
xarray_ms-0.3.8.dist-info/METADATA
xarray_ms-0.3.8.dist-info/WHEEL
xarray_ms-0.3.8.dist-info/entry_points.txt
xarray_ms-0.3.8.dist-info/licenses/LICENSE
xarray_ms-0.3.8.dist-info/RECORD
